llmcost/__init__.py
llmcost-0.0.1.dist-info/LICENCE
llmcost-0.0.1.dist-info/METADATA
llmcost-0.0.1.dist-info/WHEEL
llmcost-0.0.1.dist-info/top_level.txt
llmcost-0.0.1.dist-info/RECORD
