Metadata-Version: 2.1
Name: llmcost
Version: 0.0.1
Summary: llmcost
Author: Taranjeet Singh
Classifier: Programming Language :: Python :: 3
Classifier: License :: OSI Approved :: MIT License
Classifier: Operating System :: OS Independent
Requires-Python: >=3.6
License-File: LICENCE
